ceem/__init__.py
ceem/baseline_utils.py
ceem/ceem.py
ceem/data_utils.py
ceem/dynamics.py
ceem/exp_utils.py
ceem/learner.py
ceem/logger.py
ceem/nested.py
ceem/nn.py
ceem/odesolver.py
ceem/opt_criteria.py
ceem/particleem.py
ceem/smoother.py
ceem/utils.py
ceem/systems/__init__.py
ceem/systems/discretelinear.py
ceem/systems/lorenzattractor.py
ceem/systems/lorenzsystem.py
ceem/systems/maglev.py
ceem/systems/springmassdamper.py
CEEM-0.0.4.dist-info/LICENSE
CEEM-0.0.4.dist-info/METADATA
CEEM-0.0.4.dist-info/WHEEL
CEEM-0.0.4.dist-info/top_level.txt
CEEM-0.0.4.dist-info/zip-safe
CEEM-0.0.4.dist-info/RECORD
