Metadata-Version: 2.1
Name: CEEM
Version: 0.0.4
Summary: Official implementation of CE-EM algorithm
Home-page: https://github.com/sisl/CEEM
Author: Kunal Menda, Jayesh K. Gupta, Jean de Becdelièvre
Author-email: 
License: MIT
Platform: UNKNOWN
Classifier: Programming Language :: Python :: 3
Classifier: License :: OSI Approved :: MIT License
Classifier: Operating System :: OS Independent
Classifier: Development Status :: 4 - Beta
Requires-Python: >=3.6
Requires-Dist: click
Requires-Dist: joblib
Requires-Dist: pandas
Requires-Dist: matplotlib
Requires-Dist: numpy
Requires-Dist: scipy
Requires-Dist: torch
Requires-Dist: termcolor
Requires-Dist: python-dateutil
Requires-Dist: tensorboard
Requires-Dist: future
Requires-Dist: tqdm
Requires-Dist: pytest
